PandaSQLite/__init__.py
PandaSQLite/decorator.py
PandaSQLite/errors.py
PandaSQLite/io.py
PandaSQLite/pandasqlite.py
PandaSQLite-1.1.dist-info/AUTHORS
PandaSQLite-1.1.dist-info/LICENSE.txt
PandaSQLite-1.1.dist-info/METADATA
PandaSQLite-1.1.dist-info/WHEEL
PandaSQLite-1.1.dist-info/top_level.txt
PandaSQLite-1.1.dist-info/RECORD
