Metadata-Version: 2.1
Name: PandaSQLite
Version: 1.1
Summary: PandaSQLite is a lightweight library that combines the power of SQLite databases with the ease of use of Python numerical libraries like pandas, numpy, scipy, etc.
Home-page: https://github.com/MarcelFerrari/PandaSQLite
Download-URL: https://github.com/MarcelFerrari/PandaSQLite/archive/refs/tags/v1.1.tar.gz
Author: Marcel Ferrari
Author-email: marcel.mfnc@gmail.com
License: MIT
Keywords: Pandas,SQL,Database,Numerical Python,SQLite,Data science,Jupyter notebook
Classifier: Development Status :: 4 - Beta
Classifier: Intended Audience :: Developers
Classifier: License :: OSI Approved :: MIT License
Classifier: Programming Language :: Python :: 3
License-File: LICENSE.txt
License-File: AUTHORS
Requires-Dist: pandas
